[{"_id":"55200a0ab6241657bb270e57","会社名":"中外鉱業(株)【1491】","証券コード":"1491","決算期":"2014年3月期","会計方式":"日本方式","決算発表日":"2014年5月14日","決算月数":"12か月","売上高":"14,578百万円","営業利益":"468百万円","経常利益":"415百万円","当期利益":"-180百万円","EPS（一株当たり利益）":"-0.62円","調整一株当たり利益":"---","BPS（一株当たり純資産）":"26.31円","総資産":"8,824百万円","自己資本":"7,620百万円","資本金":"12,782百万円","有利子負債":"807百万円","自己資本比率":"86.4%","ROA（総資産利益率）":"-2.00%","ROE（自己資本利益率）":"-2.33%","総資産経常利益率":"4.62%","__v":0,"日付":"2015-04-04T15:58:02.163Z"},{"_id":"55200a0ab6241657bb270e58","会社名":"中外鉱業(株)【1491】","証券コード":"1491","決算期":"2013年3月期","会計方式":"日本方式","決算発表日":"2013年5月10日","決算月数":"12か月","売上高":"19,556百万円","営業利益":"1,502百万円","経常利益":"1,485百万円","当期利益":"241百万円","EPS（一株当たり利益）":"0.83円","調整一株当たり利益":"---","BPS（一株当たり純資産）":"26.92円","総資産":"9,144百万円","自己資本":"7,798百万円","資本金":"12,782百万円","有利子負債":"956百万円","自己資本比率":"85.3%","ROA（総資産利益率）":"2.71%","ROE（自己資本利益率）":"3.14%","総資産経常利益率":"16.72%","__v":0,"日付":"2015-04-04T15:58:02.164Z"},{"_id":"55200a0ab6241657bb270e59","会社名":"中外鉱業(株)【1491】","証券コード":"1491","決算期":"2012年3月期","会計方式":"日本方式","決算発表日":"2012年5月11日","決算月数":"12か月","売上高":"26,075百万円","営業利益":"211百万円","経常利益":"144百万円","当期利益":"-423百万円","EPS（一株当たり利益）":"-1.46円","調整一株当たり利益":"---","BPS（一株当たり純資産）":"26.09円","総資産":"8,623百万円","自己資本":"7,556百万円","資本金":"12,782百万円","有利子負債":"709百万円","自己資本比率":"87.6%","ROA（総資産利益率）":"-4.71%","ROE（自己資本利益率）":"-5.45%","総資産経常利益率":"1.60%","__v":0,"日付":"2015-04-04T15:58:02.164Z"}]