[{"_id":"5641e8f6fd1ef1594b89c869","決算期":"2008年3月期","証券コード":"1725","会社名":"(株)フジタ【1725】","会計方式":"日本方式","決算発表日":"2008年5月14日","決算月数":"12か月","売上高":"350,110百万円","営業利益":"10,238百万円","経常利益":"8,515百万円","当期利益":"10,633百万円","EPS（一株当たり利益）":"22.80円","調整一株当たり利益":"22.75円","BPS（一株当たり純資産）":"-15.53円","総資産":"208,733百万円","自己資本":"34,488百万円","資本金":"14,001百万円","有利子負債":"6,703百万円","自己資本比率":"16.5%","ROA（総資産利益率）":"4.72%","ROE（自己資本利益率）":"34.92%","総資産経常利益率":"3.78%","日付":"2015-11-10T12:55:42.747Z"},{"_id":"5641e8f6fd1ef1594b89c86a","決算期":"2007年3月期","証券コード":"1725","会社名":"(株)フジタ【1725】","会計方式":"日本方式","決算発表日":"2007年5月14日","決算月数":"12か月","売上高":"351,288百万円","営業利益":"9,327百万円","経常利益":"8,444百万円","当期利益":"7,514百万円","EPS（一株当たり利益）":"14.48円","調整一株当たり利益":"14.44円","BPS（一株当たり純資産）":"-36.46円","総資産":"241,823百万円","自己資本":"26,416百万円","資本金":"14,000百万円","有利子負債":"3,328百万円","自己資本比率":"10.9%","ROA（総資産利益率）":"3.22%","ROE（自己資本利益率）":"28.09%","総資産経常利益率":"3.62%","日付":"2015-11-10T12:55:42.747Z"},{"_id":"5641e8f6fd1ef1594b89c86b","決算期":"2006年3月期","証券コード":"1725","会社名":"(株)フジタ【1725】","会計方式":"日本方式","決算発表日":"2006年5月19日","決算月数":"12か月","売上高":"323,830百万円","営業利益":"7,890百万円","経常利益":"5,720百万円","当期利益":"102,144百万円","EPS（一株当たり利益）":"482.88円","調整一株当たり利益":"428.65円","BPS（一株当たり純資産）":"-33.11円","総資産":"224,686百万円","自己資本":"27,074百万円","資本金":"14,000百万円","有利子負債":"3,398百万円","自己資本比率":"12.0%","ROA（総資産利益率）":"41.50%","ROE（自己資本利益率）":"---","総資産経常利益率":"2.32%","日付":"2015-11-10T12:55:42.747Z"}]