[{"_id":"5641e95bfd1ef1594b89d201","決算期":"2015年3月期","証券コード":"1832","会社名":"北海電気工事(株)【1832】","会計方式":"日本方式","決算発表日":"2015年4月27日","決算月数":"12か月","売上高":"45,454百万円","営業利益":"-2,217百万円","経常利益":"-2,028百万円","当期利益":"-1,765百万円","EPS（一株当たり利益）":"-91.53円","調整一株当たり利益":"---","BPS（一株当たり純資産）":"989.11円","総資産":"32,855百万円","自己資本":"19,079百万円","資本金":"1,730百万円","有利子負債":"---","自己資本比率":"58.1%","ROA（総資産利益率）":"-5.26%","ROE（自己資本利益率）":"-8.71%","総資産経常利益率":"-6.05%","日付":"2015-11-10T12:55:56.639Z"},{"_id":"5641e95bfd1ef1594b89d202","決算期":"2013年3月期","証券コード":"1832","会社名":"北海電気工事(株)【1832】","会計方式":"日本方式","決算発表日":"2013年5月8日","決算月数":"12か月","売上高":"52,092百万円","営業利益":"587百万円","経常利益":"802百万円","当期利益":"508百万円","EPS（一株当たり利益）":"26.35円","調整一株当たり利益":"---","BPS（一株当たり純資産）":"1,103.44円","総資産":"34,983百万円","自己資本":"21,294百万円","資本金":"1,730百万円","有利子負債":"---","自己資本比率":"60.9%","ROA（総資産利益率）":"1.48%","ROE（自己資本利益率）":"2.41%","総資産経常利益率":"2.33%","日付":"2015-11-10T12:55:56.641Z"},{"_id":"5641e95bfd1ef1594b89d203","決算期":"2014年3月期","証券コード":"1832","会社名":"北海電気工事(株)【1832】","会計方式":"日本方式","決算発表日":"2014年5月8日","決算月数":"12か月","売上高":"51,201百万円","営業利益":"437百万円","経常利益":"663百万円","当期利益":"50百万円","EPS（一株当たり利益）":"2.62円","調整一株当たり利益":"---","BPS（一株当たり純資産）":"1,112.99円","総資産":"34,213百万円","自己資本":"21,469百万円","資本金":"1,730百万円","有利子負債":"---","自己資本比率":"62.8%","ROA（総資産利益率）":"0.14%","ROE（自己資本利益率）":"0.23%","総資産経常利益率":"1.92%","日付":"2015-11-10T12:55:56.641Z"}]