[{"_id":"551f897431cae9239deb1578","会社名":"(株)インサイト【2172】","証券コード":"2172","決算期":"2014年6月期","会計方式":"日本方式","決算発表日":"2014年8月14日","決算月数":"12か月","売上高":"2,156百万円","営業利益":"53百万円","経常利益":"54百万円","当期利益":"19百万円","EPS（一株当たり利益）":"12.34円","調整一株当たり利益":"---","BPS（一株当たり純資産）":"294.14円","総資産":"760百万円","自己資本":"472百万円","資本金":"139百万円","有利子負債":"7百万円","自己資本比率":"62.1%","ROA（総資産利益率）":"2.47%","ROE（自己資本利益率）":"4.06%","総資産経常利益率":"7.03%","__v":0,"日付":"2015-04-04T06:49:24.483Z"},{"_id":"551f897431cae9239deb1579","会社名":"(株)インサイト【2172】","証券コード":"2172","決算期":"2013年6月期","会計方式":"日本方式","決算発表日":"2013年8月14日","決算月数":"12か月","売上高":"1,974百万円","営業利益":"36百万円","経常利益":"53百万円","当期利益":"18百万円","EPS（一株当たり利益）":"11.91円","調整一株当たり利益":"---","BPS（一株当たり純資産）":"289.89円","総資産":"777百万円","自己資本":"465百万円","資本金":"139百万円","有利子負債":"10百万円","自己資本比率":"59.8%","ROA（総資産利益率）":"2.46%","ROE（自己資本利益率）":"3.93%","総資産経常利益率":"7.24%","__v":0,"日付":"2015-04-04T06:49:24.483Z"},{"_id":"551f897431cae9239deb157a","会社名":"(株)インサイト【2172】","証券コード":"2172","決算期":"2012年6月期","会計方式":"日本方式","決算発表日":"2012年8月14日","決算月数":"12か月","売上高":"1,663百万円","営業利益":"46百万円","経常利益":"62百万円","当期利益":"33百万円","EPS（一株当たり利益）":"64.92円","調整一株当たり利益":"---","BPS（一株当たり純資産）":"868.45円","総資産":"687百万円","自己資本":"451百万円","資本金":"135百万円","有利子負債":"---","自己資本比率":"65.6%","ROA（総資産利益率）":"4.80%","ROE（自己資本利益率）":"7.32%","総資産経常利益率":"9.02%","__v":0,"日付":"2015-04-04T06:49:24.484Z"},{"_id":"551f897431cae9239deb157b","会社名":"(株)インサイト【2172】","証券コード":"2172","決算期":"2014年6月期","会計方式":"日本方式","決算発表日":"2014年8月14日","決算月数":"12か月","売上高":"2,156百万円","営業利益":"53百万円","経常利益":"54百万円","当期利益":"19百万円","EPS（一株当たり利益）":"12.34円","調整一株当たり利益":"---","BPS（一株当たり純資産）":"294.14円","総資産":"760百万円","自己資本":"472百万円","資本金":"139百万円","有利子負債":"7百万円","自己資本比率":"62.1%","ROA（総資産利益率）":"2.47%","ROE（自己資本利益率）":"4.06%","総資産経常利益率":"7.03%","__v":0,"日付":"2015-04-04T06:49:24.488Z"},{"_id":"551f897431cae9239deb157c","会社名":"(株)インサイト【2172】","証券コード":"2172","決算期":"2013年6月期","会計方式":"日本方式","決算発表日":"2013年8月14日","決算月数":"12か月","売上高":"1,974百万円","営業利益":"36百万円","経常利益":"53百万円","当期利益":"18百万円","EPS（一株当たり利益）":"11.91円","調整一株当たり利益":"---","BPS（一株当たり純資産）":"289.89円","総資産":"777百万円","自己資本":"465百万円","資本金":"139百万円","有利子負債":"10百万円","自己資本比率":"59.8%","ROA（総資産利益率）":"2.46%","ROE（自己資本利益率）":"3.93%","総資産経常利益率":"7.24%","__v":0,"日付":"2015-04-04T06:49:24.489Z"},{"_id":"551f897431cae9239deb157d","会社名":"(株)インサイト【2172】","証券コード":"2172","決算期":"2012年6月期","会計方式":"日本方式","決算発表日":"2012年8月14日","決算月数":"12か月","売上高":"1,663百万円","営業利益":"46百万円","経常利益":"62百万円","当期利益":"33百万円","EPS（一株当たり利益）":"64.92円","調整一株当たり利益":"---","BPS（一株当たり純資産）":"868.45円","総資産":"687百万円","自己資本":"451百万円","資本金":"135百万円","有利子負債":"---","自己資本比率":"65.6%","ROA（総資産利益率）":"4.80%","ROE（自己資本利益率）":"7.32%","総資産経常利益率":"9.02%","__v":0,"日付":"2015-04-04T06:49:24.489Z"}]