[{"_id":"5562fcdbee6e1634eb05f7a1","決算期":"2014年12月期","証券コード":"2406","会社名":"(株)アルテ　サロン　ホールディングス【2406】","会計方式":"日本方式","決算発表日":"2015年2月6日","決算月数":"12か月","売上高":"6,690百万円","営業利益":"252百万円","経常利益":"304百万円","当期利益":"71百万円","EPS（一株当たり利益）":"14.15円","調整一株当たり利益":"---","BPS（一株当たり純資産）":"447.81円","総資産":"6,935百万円","自己資本":"2,250百万円","資本金":"324百万円","有利子負債":"2,408百万円","自己資本比率":"32.4%","ROA（総資産利益率）":"1.04%","ROE（自己資本利益率）":"3.17%","総資産経常利益率":"4.47%","日付":"2015-05-31T15:08:53.457Z"},{"_id":"5562fcdbee6e1634eb05f7a2","決算期":"2013年12月期","証券コード":"2406","会社名":"(株)アルテ　サロン　ホールディングス【2406】","会計方式":"日本方式","決算発表日":"2014年2月7日","決算月数":"12か月","売上高":"6,862百万円","営業利益":"425百万円","経常利益":"469百万円","当期利益":"199百万円","EPS（一株当たり利益）":"38.96円","調整一株当たり利益":"38.92円","BPS（一株当たり純資産）":"443.71円","総資産":"6,678百万円","自己資本":"2,229百万円","資本金":"324百万円","有利子負債":"2,459百万円","自己資本比率":"33.4%","ROA（総資産利益率）":"2.93%","ROE（自己資本利益率）":"9.02%","総資産経常利益率":"6.91%","日付":"2015-05-31T15:08:53.457Z"},{"_id":"5562fcdbee6e1634eb05f7a3","決算期":"2012年12月期","証券コード":"2406","会社名":"(株)アルテ　サロン　ホールディングス【2406】","会計方式":"日本方式","決算発表日":"2013年2月8日","決算月数":"12か月","売上高":"6,668百万円","営業利益":"520百万円","経常利益":"561百万円","当期利益":"190百万円","EPS（一株当たり利益）":"3,626.36円","調整一株当たり利益":"3,595.65円","BPS（一株当たり純資産）":"41,925.75円","総資産":"6,892百万円","自己資本":"2,185百万円","資本金":"324百万円","有利子負債":"2,634百万円","自己資本比率":"31.7%","ROA（総資産利益率）":"2.72%","ROE（自己資本利益率）":"8.85%","総資産経常利益率":"8.02%","日付":"2015-05-31T15:08:53.458Z"}]