[{"_id":"551f897b31cae9239deb16e6","会社名":"(株)アウトソーシング【2427】","証券コード":"2427","決算期":"2014年12月期","会計方式":"日本方式","決算発表日":"2015年2月12日","決算月数":"12か月","売上高":"59,421百万円","営業利益":"2,010百万円","経常利益":"2,197百万円","当期利益":"1,316百万円","EPS（一株当たり利益）":"89.81円","調整一株当たり利益":"88.32円","BPS（一株当たり純資産）":"463.65円","総資産":"24,132百万円","自己資本":"6,883百万円","資本金":"613百万円","有利子負債":"6,458百万円","自己資本比率":"28.5%","ROA（総資産利益率）":"5.92%","ROE（自己資本利益率）":"21.55%","総資産経常利益率":"9.88%","__v":0,"日付":"2015-04-04T06:49:31.772Z"},{"_id":"551f897b31cae9239deb16e7","会社名":"(株)アウトソーシング【2427】","証券コード":"2427","決算期":"2013年12月期","会計方式":"日本方式","決算発表日":"2014年2月13日","決算月数":"12か月","売上高":"47,384百万円","営業利益":"1,202百万円","経常利益":"1,357百万円","当期利益":"1,122百万円","EPS（一株当たり利益）":"77.54円","調整一株当たり利益":"76.02円","BPS（一株当たり純資産）":"366.71円","総資産":"20,343百万円","自己資本":"5,329百万円","資本金":"514百万円","有利子負債":"7,008百万円","自己資本比率":"26.2%","ROA（総資産利益率）":"6.56%","ROE（自己資本利益率）":"23.83%","総資産経常利益率":"7.93%","__v":0,"日付":"2015-04-04T06:49:31.772Z"},{"_id":"551f897b31cae9239deb16e8","会社名":"(株)アウトソーシング【2427】","証券コード":"2427","決算期":"2012年12月期","会計方式":"日本方式","決算発表日":"2013年2月12日","決算月数":"12か月","売上高":"42,090百万円","営業利益":"1,000百万円","経常利益":"1,153百万円","当期利益":"641百万円","EPS（一株当たり利益）":"44.46円","調整一株当たり利益":"44.39円","BPS（一株当たり純資産）":"283.24円","総資産":"13,866百万円","自己資本":"4,087百万円","資本金":"485百万円","有利子負債":"4,232百万円","自己資本比率":"29.5%","ROA（総資産利益率）":"4.97%","ROE（自己資本利益率）":"17.03%","総資産経常利益率":"8.94%","__v":0,"日付":"2015-04-04T06:49:31.773Z"},{"_id":"551f897b31cae9239deb16e9","会社名":"(株)アウトソーシング【2427】","証券コード":"2427","決算期":"2014年12月期","会計方式":"日本方式","決算発表日":"2015年2月12日","決算月数":"12か月","売上高":"59,421百万円","営業利益":"2,010百万円","経常利益":"2,197百万円","当期利益":"1,316百万円","EPS（一株当たり利益）":"89.81円","調整一株当たり利益":"88.32円","BPS（一株当たり純資産）":"463.65円","総資産":"24,132百万円","自己資本":"6,883百万円","資本金":"613百万円","有利子負債":"6,458百万円","自己資本比率":"28.5%","ROA（総資産利益率）":"5.92%","ROE（自己資本利益率）":"21.55%","総資産経常利益率":"9.88%","__v":0,"日付":"2015-04-04T06:49:31.775Z"},{"_id":"551f897b31cae9239deb16ea","会社名":"(株)アウトソーシング【2427】","証券コード":"2427","決算期":"2013年12月期","会計方式":"日本方式","決算発表日":"2014年2月13日","決算月数":"12か月","売上高":"47,384百万円","営業利益":"1,202百万円","経常利益":"1,357百万円","当期利益":"1,122百万円","EPS（一株当たり利益）":"77.54円","調整一株当たり利益":"76.02円","BPS（一株当たり純資産）":"366.71円","総資産":"20,343百万円","自己資本":"5,329百万円","資本金":"514百万円","有利子負債":"7,008百万円","自己資本比率":"26.2%","ROA（総資産利益率）":"6.56%","ROE（自己資本利益率）":"23.83%","総資産経常利益率":"7.93%","__v":0,"日付":"2015-04-04T06:49:31.775Z"},{"_id":"551f897b31cae9239deb16eb","会社名":"(株)アウトソーシング【2427】","証券コード":"2427","決算期":"2012年12月期","会計方式":"日本方式","決算発表日":"2013年2月12日","決算月数":"12か月","売上高":"42,090百万円","営業利益":"1,000百万円","経常利益":"1,153百万円","当期利益":"641百万円","EPS（一株当たり利益）":"44.46円","調整一株当たり利益":"44.39円","BPS（一株当たり純資産）":"283.24円","総資産":"13,866百万円","自己資本":"4,087百万円","資本金":"485百万円","有利子負債":"4,232百万円","自己資本比率":"29.5%","ROA（総資産利益率）":"4.97%","ROE（自己資本利益率）":"17.03%","総資産経常利益率":"8.94%","__v":0,"日付":"2015-04-04T06:49:31.775Z"}]