[{"_id":"55200a1bb6241657bb270f00","会社名":"(株)デジタルスケープ【2430】","証券コード":"2430","決算期":"2008年3月期","会計方式":"日本方式","決算発表日":"2008年5月12日","決算月数":"12か月","売上高":"9,177百万円","営業利益":"182百万円","経常利益":"141百万円","当期利益":"-579百万円","EPS（一株当たり利益）":"-19,762.67円","調整一株当たり利益":"---","BPS（一株当たり純資産）":"15,157.36円","総資産":"3,631百万円","自己資本":"444百万円","資本金":"360百万円","有利子負債":"1,548百万円","自己資本比率":"12.2%","ROA（総資産利益率）":"-14.79%","ROE（自己資本利益率）":"-77.35%","総資産経常利益率":"3.60%","__v":0,"日付":"2015-04-04T15:58:19.762Z"},{"_id":"55200a1bb6241657bb270f01","会社名":"(株)デジタルスケープ【2430】","証券コード":"2430","決算期":"2009年3月期","会計方式":"日本方式","決算発表日":"2009年5月11日","決算月数":"12か月","売上高":"8,170百万円","営業利益":"-165百万円","経常利益":"-192百万円","当期利益":"-403百万円","EPS（一株当たり利益）":"-13,772.34円","調整一株当たり利益":"---","BPS（一株当たり純資産）":"1,385.02円","総資産":"2,981百万円","自己資本":"40百万円","資本金":"360百万円","有利子負債":"1,608百万円","自己資本比率":"1.3%","ROA（総資産利益率）":"-12.19%","ROE（自己資本利益率）":"-166.53%","総資産経常利益率":"-5.81%","__v":0,"日付":"2015-04-04T15:58:19.768Z"}]