[{"_id":"551f8be317a70bec9ea29488","会社名":"(株)ファンコミュニケーションズ【2461】","証券コード":"2461","決算期":"2014年12月期","会計方式":"日本方式","決算発表日":"2015年2月9日","決算月数":"12か月","売上高":"31,990百万円","営業利益":"5,889百万円","経常利益":"5,948百万円","当期利益":"3,630百万円","EPS（一株当たり利益）":"47.14円","調整一株当たり利益":"46.54円","BPS（一株当たり純資産）":"152.57円","総資産":"18,354百万円","自己資本":"11,806百万円","資本金":"1,101百万円","有利子負債":"---","自己資本比率":"64.3%","ROA（総資産利益率）":"22.68%","ROE（自己資本利益率）":"35.60%","総資産経常利益率":"37.16%","__v":0,"日付":"2015-04-04T06:59:47.960Z"},{"_id":"551f8be317a70bec9ea29489","会社名":"(株)ファンコミュニケーションズ【2461】","証券コード":"2461","決算期":"2013年12月期","会計方式":"日本方式","決算発表日":"2014年2月7日","決算月数":"12か月","売上高":"22,721百万円","営業利益":"4,075百万円","経常利益":"4,126百万円","当期利益":"2,563百万円","EPS（一株当たり利益）":"67.58円","調整一株当たり利益":"66.29円","BPS（一株当たり純資産）":"224.69円","総資産":"13,660百万円","自己資本":"8,587百万円","資本金":"1,045百万円","有利子負債":"---","自己資本比率":"62.9%","ROA（総資産利益率）":"21.97%","ROE（自己資本利益率）":"34.89%","総資産経常利益率":"35.36%","__v":0,"日付":"2015-04-04T06:59:47.960Z"},{"_id":"551f8be317a70bec9ea2948a","会社名":"(株)ファンコミュニケーションズ【2461】","証券コード":"2461","決算期":"2012年12月期","会計方式":"日本方式","決算発表日":"2013年2月8日","決算月数":"12か月","売上高":"14,482百万円","営業利益":"2,245百万円","経常利益":"2,304百万円","当期利益":"1,639百万円","EPS（一株当たり利益）":"174.32円","調整一株当たり利益":"170.79円","BPS（一株当たり純資産）":"652.50円","総資産":"9,675百万円","自己資本":"6,104百万円","資本金":"960百万円","有利子負債":"---","自己資本比率":"63.1%","ROA（総資産利益率）":"18.93%","ROE（自己資本利益率）":"29.77%","総資産経常利益率":"26.61%","__v":0,"日付":"2015-04-04T06:59:47.960Z"}]