[{"_id":"5641e8f3fd1ef1594b89c5f0","決算期":"2015年3月期","証券コード":"3036","会社名":"アルコニックス(株)【3036】","会計方式":"日本方式","決算発表日":"2015年5月15日","決算月数":"12か月","売上高":"201,543百万円","営業利益":"4,584百万円","経常利益":"5,205百万円","当期利益":"3,505百万円","EPS（一株当たり利益）":"274.76円","調整一株当たり利益":"273.45円","BPS（一株当たり純資産）":"2,053.83円","総資産":"89,848百万円","自己資本":"26,316百万円","資本金":"2,873百万円","有利子負債":"30,130百万円","自己資本比率":"29.3%","ROA（総資産利益率）":"3.99%","ROE（自己資本利益率）":"14.87%","総資産経常利益率":"5.93%","日付":"2015-11-10T12:55:42.640Z"},{"_id":"5641e8f3fd1ef1594b89c5f1","決算期":"2014年3月期","証券コード":"3036","会社名":"アルコニックス(株)【3036】","会計方式":"日本方式","決算発表日":"2014年5月16日","決算月数":"12か月","売上高":"183,749百万円","営業利益":"3,484百万円","経常利益":"3,600百万円","当期利益":"3,144百万円","EPS（一株当たり利益）":"494.77円","調整一株当たり利益":"493.00円","BPS（一株当たり純資産）":"3,276.42円","総資産":"85,664百万円","自己資本":"20,835百万円","資本金":"2,835百万円","有利子負債":"29,912百万円","自己資本比率":"24.3%","ROA（総資産利益率）":"4.03%","ROE（自己資本利益率）":"17.38%","総資産経常利益率":"4.61%","日付":"2015-11-10T12:55:42.640Z"},{"_id":"5641e8f3fd1ef1594b89c5f2","決算期":"2013年3月期","証券コード":"3036","会社名":"アルコニックス(株)【3036】","会計方式":"日本方式","決算発表日":"2013年5月17日","決算月数":"12か月","売上高":"164,769百万円","営業利益":"3,286百万円","経常利益":"2,892百万円","当期利益":"1,430百万円","EPS（一株当たり利益）":"225.16円","調整一株当たり利益":"224.28円","BPS（一株当たり純資産）":"2,414.98円","総資産":"70,382百万円","自己資本":"15,349百万円","資本金":"2,832百万円","有利子負債":"26,925百万円","自己資本比率":"21.8%","ROA（総資産利益率）":"2.06%","ROE（自己資本利益率）":"9.87%","総資産経常利益率":"4.16%","日付":"2015-11-10T12:55:42.640Z"}]