[{"_id":"551f89a431cae9239deb1cba","会社名":"ジャパンインベスト・グループ【3827】","証券コード":"3827","決算期":"2014年12月期","会計方式":"英国方式","決算発表日":"2015年2月13日","決算月数":"12か月","売上高":"1,552百万円","営業利益":"-149百万円","経常利益":"-149百万円","当期利益":"-149百万円","EPS（一株当たり利益）":"-1,260.45円","調整一株当たり利益":"-1,260.45円","BPS（一株当たり純資産）":"216.93円","総資産":"651百万円","自己資本":"26百万円","資本金":"22百万円","有利子負債":"625百万円","自己資本比率":"4%","ROA（総資産利益率）":"-27.85%","ROE（自己資本利益率）":"-281.13%","総資産経常利益率":"-27.85%","__v":0,"日付":"2015-04-04T06:50:12.217Z"},{"_id":"551f89a431cae9239deb1cbb","会社名":"ジャパンインベスト・グループ【3827】","証券コード":"3827","決算期":"2013年12月期","会計方式":"英国方式","決算発表日":"2014年2月10日","決算月数":"12か月","売上高":"1,342百万円","営業利益":"---","経常利益":"---","当期利益":"18百万円","EPS（一株当たり利益）":"161.58円","調整一株当たり利益":"132.04円","BPS（一株当たり純資産）":"696.70円","総資産":"419百万円","自己資本":"80百万円","資本金":"20百万円","有利子負債":"338百万円","自己資本比率":"19.3%","ROA（総資産利益率）":"4.55%","ROE（自己資本利益率）":"34.29%","総資産経常利益率":"---","__v":0,"日付":"2015-04-04T06:50:12.217Z"},{"_id":"551f89a431cae9239deb1cbc","会社名":"ジャパンインベスト・グループ【3827】","証券コード":"3827","決算期":"2012年12月期","会計方式":"英国方式","決算発表日":"2013年2月13日","決算月数":"12か月","売上高":"1,030百万円","営業利益":"-26百万円","経常利益":"-26百万円","当期利益":"-26百万円","EPS（一株当たり利益）":"-265.11円","調整一株当たり利益":"---","BPS（一株当たり純資産）":"231.62円","総資産":"373百万円","自己資本":"25百万円","資本金":"15百万円","有利子負債":"325百万円","自己資本比率":"6.9%","ROA（総資産利益率）":"-8.05%","ROE（自己資本利益率）":"---","総資産経常利益率":"-8.05%","__v":0,"日付":"2015-04-04T06:50:12.217Z"}]