[{"_id":"5641e8f6fd1ef1594b89c85d","決算期":"2014年11月期","証券コード":"3907","会社名":"シリコンスタジオ(株)【3907】","会計方式":"日本方式","決算発表日":"‐年0月0日","決算月数":"12か月","売上高":"8,056百万円","営業利益":"841百万円","経常利益":"832百万円","当期利益":"507百万円","EPS（一株当たり利益）":"255.82円","調整一株当たり利益":"---","BPS（一株当たり純資産）":"781.76円","総資産":"4,163百万円","自己資本":"1,565百万円","資本金":"100百万円","有利子負債":"1,341百万円","自己資本比率":"37.6%","ROA（総資産利益率）":"12.85%","ROE（自己資本利益率）":"38.82%","総資産経常利益率":"21.08%","日付":"2015-11-10T12:55:42.791Z"},{"_id":"5641e8f6fd1ef1594b89c85e","決算期":"2013年11月期","証券コード":"3907","会社名":"シリコンスタジオ(株)【3907】","会計方式":"日本方式","決算発表日":"‐年0月0日","決算月数":"12か月","売上高":"7,264百万円","営業利益":"556百万円","経常利益":"565百万円","当期利益":"395百万円","EPS（一株当たり利益）":"170.31円","調整一株当たり利益":"---","BPS（一株当たり純資産）":"533.11円","総資産":"3,729百万円","自己資本":"1,047百万円","資本金":"100百万円","有利子負債":"1,118百万円","自己資本比率":"28.1%","ROA（総資産利益率）":"13.02%","ROE（自己資本利益率）":"41.38%","総資産経常利益率":"18.63%","日付":"2015-11-10T12:55:42.791Z"},{"_id":"5641e8f6fd1ef1594b89c85f","決算期":"2012年11月期","証券コード":"3907","会社名":"シリコンスタジオ(株)【3907】","会計方式":"日本方式","決算発表日":"‐年0月0日","決算月数":"12か月","売上高":"5,770百万円","営業利益":"560百万円","経常利益":"558百万円","当期利益":"328百万円","EPS（一株当たり利益）":"41,882.50円","調整一株当たり利益":"---","BPS（一株当たり純資産）":"109,890.47円","総資産":"2,338百万円","自己資本":"862百万円","資本金":"100百万円","有利子負債":"623百万円","自己資本比率":"36.9%","ROA（総資産利益率）":"14.03%","ROE（自己資本利益率）":"38.05%","総資産経常利益率":"23.87%","日付":"2015-11-10T12:55:42.791Z"}]