[{"_id":"551f89bf31cae9239deb207e","会社名":"(株)オープンループ【4831】","証券コード":"4831","決算期":"2008年9月期","会計方式":"日本方式","決算発表日":"2008年11月19日","決算月数":"12か月","売上高":"6,335百万円","営業利益":"-269百万円","経常利益":"-262百万円","当期利益":"-479百万円","EPS（一株当たり利益）":"-5,413.41円","調整一株当たり利益":"---","BPS（一株当たり純資産）":"27,363.92円","総資産":"3,492百万円","自己資本":"2,424百万円","資本金":"1,050百万円","有利子負債":"---","自己資本比率":"69.4%","ROA（総資産利益率）":"-13.48%","ROE（自己資本利益率）":"-18.08%","総資産経常利益率":"-7.38%","__v":0,"日付":"2015-04-04T06:50:39.065Z"},{"_id":"551f89bf31cae9239deb207f","会社名":"(株)オープンループ【4831】","証券コード":"4831","決算期":"2007年9月期","会計方式":"日本方式","決算発表日":"2007年11月22日","決算月数":"12か月","売上高":"5,817百万円","営業利益":"-71百万円","経常利益":"-48百万円","当期利益":"-602百万円","EPS（一株当たり利益）":"-6,903.28円","調整一株当たり利益":"---","BPS（一株当たり純資産）":"32,448.91円","総資産":"3,613百万円","自己資本":"2,874百万円","資本金":"1,050百万円","有利子負債":"60百万円","自己資本比率":"79.5%","ROA（総資産利益率）":"-15.64%","ROE（自己資本利益率）":"-19.04%","総資産経常利益率":"-1.25%","__v":0,"日付":"2015-04-04T06:50:39.065Z"},{"_id":"551f89bf31cae9239deb2080","会社名":"(株)オープンループ【4831】","証券コード":"4831","決算期":"2006年9月期","会計方式":"日本方式","決算発表日":"2006年11月21日","決算月数":"12か月","売上高":"5,002百万円","営業利益":"-445百万円","経常利益":"-480百万円","当期利益":"462百万円","EPS（一株当たり利益）":"5,797.30円","調整一株当たり利益":"5,788.73円","BPS（一株当たり純資産）":"40,086.23円","総資産":"4,087百万円","自己資本":"3,448百万円","資本金":"4,770百万円","有利子負債":"120百万円","自己資本比率":"84.4%","ROA（総資産利益率）":"12.43%","ROE（自己資本利益率）":"18.36%","総資産経常利益率":"-12.91%","__v":0,"日付":"2015-04-04T06:50:39.066Z"},{"_id":"551f89bf31cae9239deb2083","会社名":"(株)オープンループ【4831】","証券コード":"4831","決算期":"2006年9月期","会計方式":"日本方式","決算発表日":"2006年11月21日","決算月数":"12か月","売上高":"5,002百万円","営業利益":"-445百万円","経常利益":"-480百万円","当期利益":"462百万円","EPS（一株当たり利益）":"5,797.30円","調整一株当たり利益":"5,788.73円","BPS（一株当たり純資産）":"40,086.23円","総資産":"4,087百万円","自己資本":"3,448百万円","資本金":"4,770百万円","有利子負債":"120百万円","自己資本比率":"84.4%","ROA（総資産利益率）":"12.43%","ROE（自己資本利益率）":"18.36%","総資産経常利益率":"-12.91%","__v":0,"日付":"2015-04-04T06:50:39.069Z"},{"_id":"551f89bf31cae9239deb2081","会社名":"(株)オープンループ【4831】","証券コード":"4831","決算期":"2008年9月期","会計方式":"日本方式","決算発表日":"2008年11月19日","決算月数":"12か月","売上高":"6,335百万円","営業利益":"-269百万円","経常利益":"-262百万円","当期利益":"-479百万円","EPS（一株当たり利益）":"-5,413.41円","調整一株当たり利益":"---","BPS（一株当たり純資産）":"27,363.92円","総資産":"3,492百万円","自己資本":"2,424百万円","資本金":"1,050百万円","有利子負債":"---","自己資本比率":"69.4%","ROA（総資産利益率）":"-13.48%","ROE（自己資本利益率）":"-18.08%","総資産経常利益率":"-7.38%","__v":0,"日付":"2015-04-04T06:50:39.068Z"},{"_id":"551f89bf31cae9239deb2082","会社名":"(株)オープンループ【4831】","証券コード":"4831","決算期":"2007年9月期","会計方式":"日本方式","決算発表日":"2007年11月22日","決算月数":"12か月","売上高":"5,817百万円","営業利益":"-71百万円","経常利益":"-48百万円","当期利益":"-602百万円","EPS（一株当たり利益）":"-6,903.28円","調整一株当たり利益":"---","BPS（一株当たり純資産）":"32,448.91円","総資産":"3,613百万円","自己資本":"2,874百万円","資本金":"1,050百万円","有利子負債":"60百万円","自己資本比率":"79.5%","ROA（総資産利益率）":"-15.64%","ROE（自己資本利益率）":"-19.04%","総資産経常利益率":"-1.25%","__v":0,"日付":"2015-04-04T06:50:39.069Z"}]