[{"会社名":"新日本石油(株)【5001】","証券コード":"5001","　":"前期","決算期":"2009年3月期","会計方式":"日本方式","決算発表日":"2009年4月30日","決算月数":"12か月","売上高":"7,389,234百万円","営業利益":"-312,506百万円","経常利益":"-275,448百万円","当期利益":"-251,613百万円","EPS（一株当たり利益）":"-172.42円","調整一株当たり利益":"---","BPS（一株当たり純資産）":"627.90円","総資産":"3,969,730百万円","自己資本":"915,406百万円","資本金":"139,437百万円","有利子負債":"1,417,453百万円","自己資本比率":"23.1%","ROA（総資産利益率）":"-5.88%","ROE（自己資本利益率）":"-22.61%","総資産経常利益率":"-6.43%"},{"会社名":"新日本石油(株)【5001】","証券コード":"5001","　":"2期前","決算期":"2008年3月期","会計方式":"日本方式","決算発表日":"2008年4月28日","決算月数":"12か月","売上高":"7,523,990百万円","営業利益":"263,962百万円","経常利益":"275,666百万円","当期利益":"148,306百万円","EPS（一株当たり利益）":"101.49円","調整一株当たり利益":"---","BPS（一株当たり純資産）":"896.06円","総資産":"4,594,197百万円","自己資本":"1,309,788百万円","資本金":"139,437百万円","有利子負債":"1,336,605百万円","自己資本比率":"28.5%","ROA（総資産利益率）":"3.30%","ROE（自己資本利益率）":"11.76%","総資産経常利益率":"6.14%"},{"会社名":"新日本石油(株)【5001】","証券コード":"5001","　":"3期前","決算期":"2007年3月期","会計方式":"日本方式","決算発表日":"2007年4月26日","決算月数":"12か月","売上高":"6,624,256百万円","営業利益":"159,684百万円","経常利益":"186,611百万円","当期利益":"70,221百万円","EPS（一株当たり利益）":"48.12円","調整一株当たり利益":"---","BPS（一株当たり純資産）":"829.64円","総資産":"4,385,533百万円","自己資本":"1,212,740百万円","資本金":"139,437百万円","有利子負債":"1,292,120百万円","自己資本比率":"27.7%","ROA（総資産利益率）":"1.63%","ROE（自己資本利益率）":"5.99%","総資産経常利益率":"4.33%"}]