[{"_id":"556499f5fac443afdd3939a4","決算期":"2009年3月期","証券コード":"5383","会社名":"三共理化学(株)【5383】","会計方式":"日本方式","決算発表日":"2009年5月15日","決算月数":"12か月","売上高":"13,102百万円","営業利益":"582百万円","経常利益":"532百万円","当期利益":"350百万円","EPS（一株当たり利益）":"67.68円","調整一株当たり利益":"---","BPS（一株当たり純資産）":"2,049.78円","総資産":"14,149百万円","自己資本":"10,265百万円","資本金":"573百万円","有利子負債":"1,201百万円","自己資本比率":"72.5%","ROA（総資産利益率）":"2.43%","ROE（自己資本利益率）":"3.38%","総資産経常利益率":"3.69%","日付":"2015-05-26T16:06:13.258Z"},{"_id":"556499f5fac443afdd3939a5","決算期":"2008年3月期","証券コード":"5383","会社名":"三共理化学(株)【5383】","会計方式":"日本方式","決算発表日":"2008年5月15日","決算月数":"12か月","売上高":"15,254百万円","営業利益":"1,274百万円","経常利益":"1,247百万円","当期利益":"734百万円","EPS（一株当たり利益）":"134.44円","調整一株当たり利益":"---","BPS（一株当たり純資産）":"2,005.03円","総資産":"14,653百万円","自己資本":"10,443百万円","資本金":"573百万円","有利子負債":"2百万円","自己資本比率":"71.3%","ROA（総資産利益率）":"4.97%","ROE（自己資本利益率）":"6.96%","総資産経常利益率":"8.45%","日付":"2015-05-26T16:06:13.258Z"},{"_id":"556499f5fac443afdd3939a6","決算期":"2007年3月期","証券コード":"5383","会社名":"三共理化学(株)【5383】","会計方式":"日本方式","決算発表日":"2007年5月15日","決算月数":"12か月","売上高":"15,082百万円","営業利益":"1,223百万円","経常利益":"1,251百万円","当期利益":"709百万円","EPS（一株当たり利益）":"122.74円","調整一株当たり利益":"---","BPS（一株当たり純資産）":"1,837.49円","総資産":"14,856百万円","自己資本":"10,637百万円","資本金":"573百万円","有利子負債":"124百万円","自己資本比率":"71.6%","ROA（総資産利益率）":"4.83%","ROE（自己資本利益率）":"6.86%","総資産経常利益率":"8.52%","日付":"2015-05-26T16:06:13.258Z"}]