[{"_id":"551f89dd31cae9239deb2352","会社名":"協立エアテック(株)【5997】","証券コード":"5997","決算期":"2014年12月期","会計方式":"日本方式","決算発表日":"2015年2月13日","決算月数":"12か月","売上高":"8,078百万円","営業利益":"496百万円","経常利益":"542百万円","当期利益":"285百万円","EPS（一株当たり利益）":"54.00円","調整一株当たり利益":"---","BPS（一株当たり純資産）":"813.01円","総資産":"9,299百万円","自己資本":"4,305百万円","資本金":"1,683百万円","有利子負債":"1,458百万円","自己資本比率":"46.3%","ROA（総資産利益率）":"3.27%","ROE（自己資本利益率）":"6.76%","総資産経常利益率":"6.22%","__v":0,"日付":"2015-04-04T06:51:09.808Z"},{"_id":"551f89dd31cae9239deb2353","会社名":"協立エアテック(株)【5997】","証券コード":"5997","決算期":"2013年12月期","会計方式":"日本方式","決算発表日":"2014年2月14日","決算月数":"12か月","売上高":"7,414百万円","営業利益":"277百万円","経常利益":"345百万円","当期利益":"163百万円","EPS（一株当たり利益）":"30.95円","調整一株当たり利益":"---","BPS（一株当たり純資産）":"780.39円","総資産":"8,137百万円","自己資本":"4,132百万円","資本金":"1,683百万円","有利子負債":"1,364百万円","自己資本比率":"50.8%","ROA（総資産利益率）":"1.91%","ROE（自己資本利益率）":"4.01%","総資産経常利益率":"4.04%","__v":0,"日付":"2015-04-04T06:51:09.809Z"},{"_id":"551f89dd31cae9239deb2354","会社名":"協立エアテック(株)【5997】","証券コード":"5997","決算期":"2012年12月期","会計方式":"日本方式","決算発表日":"2013年2月15日","決算月数":"12か月","売上高":"7,949百万円","営業利益":"443百万円","経常利益":"473百万円","当期利益":"262百万円","EPS（一株当たり利益）":"49.49円","調整一株当たり利益":"---","BPS（一株当たり純資産）":"753.75円","総資産":"8,939百万円","自己資本":"3,992百万円","資本金":"1,683百万円","有利子負債":"1,820百万円","自己資本比率":"44.7%","ROA（総資産利益率）":"2.99%","ROE（自己資本利益率）":"6.75%","総資産経常利益率":"5.41%","__v":0,"日付":"2015-04-04T06:51:09.809Z"}]