[{"_id":"551f89dd31cae9239deb2355","会社名":"(株)アドバネクス【5998】","証券コード":"5998","決算期":"2014年3月期","会計方式":"日本方式","決算発表日":"2014年5月9日","決算月数":"12か月","売上高":"27,100百万円","営業利益":"820百万円","経常利益":"820百万円","当期利益":"682百万円","EPS（一株当たり利益）":"16.45円","調整一株当たり利益":"16.39円","BPS（一株当たり純資産）":"114.04円","総資産":"20,240百万円","自己資本":"4,729百万円","資本金":"1,000百万円","有利子負債":"6,896百万円","自己資本比率":"23.4%","ROA（総資産利益率）":"3.52%","ROE（自己資本利益率）":"15.53%","総資産経常利益率":"4.24%","__v":0,"日付":"2015-04-04T06:51:09.845Z"},{"_id":"551f89dd31cae9239deb2356","会社名":"(株)アドバネクス【5998】","証券コード":"5998","決算期":"2013年3月期","会計方式":"日本方式","決算発表日":"2013年5月10日","決算月数":"12か月","売上高":"23,551百万円","営業利益":"426百万円","経常利益":"542百万円","当期利益":"478百万円","EPS（一株当たり利益）":"11.52円","調整一株当たり利益":"---","BPS（一株当たり純資産）":"97.75円","総資産":"18,469百万円","自己資本":"4,056百万円","資本金":"1,000百万円","有利子負債":"7,268百万円","自己資本比率":"22.0%","ROA（総資産利益率）":"2.59%","ROE（自己資本利益率）":"14.03%","総資産経常利益率":"2.94%","__v":0,"日付":"2015-04-04T06:51:09.846Z"},{"_id":"551f89dd31cae9239deb2357","会社名":"(株)アドバネクス【5998】","証券コード":"5998","決算期":"2012年3月期","会計方式":"日本方式","決算発表日":"2012年5月11日","決算月数":"12か月","売上高":"25,191百万円","営業利益":"612百万円","経常利益":"470百万円","当期利益":"226百万円","EPS（一株当たり利益）":"5.60円","調整一株当たり利益":"---","BPS（一株当たり純資産）":"66.37円","総資産":"18,416百万円","自己資本":"2,756百万円","資本金":"3,451百万円","有利子負債":"8,069百万円","自己資本比率":"15.0%","ROA（総資産利益率）":"1.15%","ROE（自己資本利益率）":"8.67%","総資産経常利益率":"2.40%","__v":0,"日付":"2015-04-04T06:51:09.846Z"}]