[{"_id":"551f89f831cae9239deb2721","会社名":"(株)パトライト【6825】","証券コード":"6825","決算期":"2007年3月期","会計方式":"日本方式","決算発表日":"2007年5月10日","決算月数":"12か月","売上高":"11,609百万円","営業利益":"1,682百万円","経常利益":"1,733百万円","当期利益":"1,819百万円","EPS（一株当たり利益）":"87.71円","調整一株当たり利益":"87.46円","BPS（一株当たり純資産）":"1,022.56円","総資産":"25,268百万円","自己資本":"21,288百万円","資本金":"2,828百万円","有利子負債":"45百万円","自己資本比率":"84.2%","ROA（総資産利益率）":"7.45%","ROE（自己資本利益率）":"8.86%","総資産経常利益率":"7.10%","__v":0,"日付":"2015-04-04T06:51:36.689Z"},{"_id":"551f89f831cae9239deb2722","会社名":"(株)パトライト【6825】","証券コード":"6825","決算期":"2006年3月期","会計方式":"日本方式","決算発表日":"2006年5月16日","決算月数":"12か月","売上高":"10,759百万円","営業利益":"2,055百万円","経常利益":"2,100百万円","当期利益":"603百万円","EPS（一株当たり利益）":"28.94円","調整一株当たり利益":"28.65円","BPS（一株当たり純資産）":"955.79円","総資産":"23,575百万円","自己資本":"19,783百万円","資本金":"2,789百万円","有利子負債":"21百万円","自己資本比率":"83.9%","ROA（総資産利益率）":"2.65%","ROE（自己資本利益率）":"3.11%","総資産経常利益率":"9.23%","__v":0,"日付":"2015-04-04T06:51:36.689Z"},{"_id":"551f89f831cae9239deb2723","会社名":"(株)パトライト【6825】","証券コード":"6825","決算期":"2005年3月期","会計方式":"日本方式","決算発表日":"2005年5月17日","決算月数":"12か月","売上高":"10,741百万円","営業利益":"2,232百万円","経常利益":"2,242百万円","当期利益":"1,367百万円","EPS（一株当たり利益）":"137.95円","調整一株当たり利益":"135.20円","BPS（一株当たり純資産）":"1,869.08円","総資産":"21,914百万円","自己資本":"19,042百万円","資本金":"2,682百万円","有利子負債":"---","自己資本比率":"86.9%","ROA（総資産利益率）":"6.61%","ROE（自己資本利益率）":"7.70%","総資産経常利益率":"10.84%","__v":0,"日付":"2015-04-04T06:51:36.689Z"}]