[{"_id":"5641e958fd1ef1594b89cfc1","決算期":"2015年3月期","証券コード":"6864","会社名":"(株)エヌエフ回路設計ブロック【6864】","会計方式":"日本方式","決算発表日":"2015年5月15日","決算月数":"12か月","売上高":"8,309百万円","営業利益":"1,085百万円","経常利益":"1,060百万円","当期利益":"634百万円","EPS（一株当たり利益）":"108.31円","調整一株当たり利益":"---","BPS（一株当たり純資産）":"1,092.11円","総資産":"10,949百万円","自己資本":"6,857百万円","資本金":"953百万円","有利子負債":"1,442百万円","自己資本比率":"62.6%","ROA（総資産利益率）":"6.08%","ROE（自己資本利益率）":"9.90%","総資産経常利益率":"10.16%","日付":"2015-11-10T12:55:55.406Z"},{"_id":"5641e958fd1ef1594b89cfc2","決算期":"2014年3月期","証券コード":"6864","会社名":"(株)エヌエフ回路設計ブロック【6864】","会計方式":"日本方式","決算発表日":"2014年5月15日","決算月数":"12か月","売上高":"7,350百万円","営業利益":"962百万円","経常利益":"933百万円","当期利益":"888百万円","EPS（一株当たり利益）":"152.63円","調整一株当たり利益":"---","BPS（一株当たり純資産）":"1,022.54円","総資産":"9,912百万円","自己資本":"5,951百万円","資本金":"910百万円","有利子負債":"1,704百万円","自己資本比率":"60.0%","ROA（総資産利益率）":"9.46%","ROE（自己資本利益率）":"15.93%","総資産経常利益率":"9.94%","日付":"2015-11-10T12:55:55.406Z"},{"_id":"5641e958fd1ef1594b89cfc3","決算期":"2013年3月期","証券コード":"6864","会社名":"(株)エヌエフ回路設計ブロック【6864】","会計方式":"日本方式","決算発表日":"2013年5月15日","決算月数":"12か月","売上高":"6,605百万円","営業利益":"836百万円","経常利益":"835百万円","当期利益":"503百万円","EPS（一株当たり利益）":"86.41円","調整一株当たり利益":"---","BPS（一株当たり純資産）":"892.62円","総資産":"8,868百万円","自己資本":"5,198百万円","資本金":"910百万円","有利子負債":"1,778百万円","自己資本比率":"58.6%","ROA（総資産利益率）":"5.73%","ROE（自己資本利益率）":"10.12%","総資産経常利益率":"9.51%","日付":"2015-11-10T12:55:55.407Z"}]