[{"_id":"5562fdbeee6e1634eb060f73","決算期":"2014年9月期","証券コード":"7432","会社名":"(株)ダルトン【7432】","会計方式":"日本方式","決算発表日":"2014年11月11日","決算月数":"12か月","売上高":"16,785百万円","営業利益":"439百万円","経常利益":"350百万円","当期利益":"239百万円","EPS（一株当たり利益）":"17.13円","調整一株当たり利益":"---","BPS（一株当たり純資産）":"240.94円","総資産":"15,089百万円","自己資本":"3,372百万円","資本金":"1,387百万円","有利子負債":"4,905百万円","自己資本比率":"22.3%","ROA（総資産利益率）":"1.59%","ROE（自己資本利益率）":"6.96%","総資産経常利益率":"2.32%","日付":"2015-05-31T15:08:45.699Z"},{"_id":"5562fdbeee6e1634eb060f74","決算期":"2013年9月期","証券コード":"7432","会社名":"(株)ダルトン【7432】","会計方式":"日本方式","決算発表日":"2013年11月8日","決算月数":"12か月","売上高":"15,160百万円","営業利益":"85百万円","経常利益":"-8百万円","当期利益":"-202百万円","EPS（一株当たり利益）":"-14.45円","調整一株当たり利益":"---","BPS（一株当たり純資産）":"249.49円","総資産":"15,025百万円","自己資本":"3,492百万円","資本金":"1,387百万円","有利子負債":"5,393百万円","自己資本比率":"23.2%","ROA（総資産利益率）":"-1.42%","ROE（自己資本利益率）":"-5.64%","総資産経常利益率":"-0.06%","日付":"2015-05-31T15:08:45.700Z"},{"_id":"5562fdbeee6e1634eb060f75","決算期":"2012年9月期","証券コード":"7432","会社名":"(株)ダルトン【7432】","会計方式":"日本方式","決算発表日":"2012年11月12日","決算月数":"12か月","売上高":"17,293百万円","営業利益":"416百万円","経常利益":"309百万円","当期利益":"269百万円","EPS（一株当たり利益）":"19.27円","調整一株当たり利益":"---","BPS（一株当たり純資産）":"262.61円","総資産":"13,457百万円","自己資本":"3,676百万円","資本金":"1,387百万円","有利子負債":"3,807百万円","自己資本比率":"27.3%","ROA（総資産利益率）":"2.07%","ROE（自己資本利益率）":"7.60%","総資産経常利益率":"2.37%","日付":"2015-05-31T15:08:45.700Z"}]