[{"_id":"556b2a6cfac443afdd3942a8","決算期":"2015年3月期","証券コード":"7565","会社名":"萬世電機(株)【7565】","会計方式":"日本方式","決算発表日":"2015年5月11日","決算月数":"12か月","売上高":"22,022百万円","営業利益":"627百万円","経常利益":"683百万円","当期利益":"1,793百万円","EPS（一株当たり利益）":"391.33円","調整一株当たり利益":"---","BPS（一株当たり純資産）":"2,119.89円","総資産":"17,718百万円","自己資本":"9,707百万円","資本金":"1,005百万円","有利子負債":"350百万円","自己資本比率":"54.8%","ROA（総資産利益率）":"11.05%","ROE（自己資本利益率）":"20.36%","総資産経常利益率":"4.21%","日付":"2015-05-31T15:36:12.867Z"},{"_id":"556b2a6cfac443afdd3942a9","決算期":"2014年3月期","証券コード":"7565","会社名":"萬世電機(株)【7565】","会計方式":"日本方式","決算発表日":"2014年5月9日","決算月数":"12か月","売上高":"20,406百万円","営業利益":"535百万円","経常利益":"541百万円","当期利益":"378百万円","EPS（一株当たり利益）":"82.56円","調整一株当たり利益":"---","BPS（一株当たり純資産）":"1,723.32円","総資産":"14,728百万円","自己資本":"7,902百万円","資本金":"1,005百万円","有利子負債":"354百万円","自己資本比率":"53.7%","ROA（総資産利益率）":"2.49%","ROE（自己資本利益率）":"4.88%","総資産経常利益率":"3.56%","日付":"2015-05-31T15:36:12.867Z"},{"_id":"556b2a6cfac443afdd3942aa","決算期":"2013年3月期","証券コード":"7565","会社名":"萬世電機(株)【7565】","会計方式":"日本方式","決算発表日":"2013年5月9日","決算月数":"12か月","売上高":"20,655百万円","営業利益":"527百万円","経常利益":"522百万円","当期利益":"257百万円","EPS（一株当たり利益）":"56.22円","調整一株当たり利益":"---","BPS（一株当たり純資産）":"1,652.77円","総資産":"15,644百万円","自己資本":"7,579百万円","資本金":"1,005百万円","有利子負債":"363百万円","自己資本比率":"48.4%","ROA（総資産利益率）":"1.65%","ROE（自己資本利益率）":"3.47%","総資産経常利益率":"3.34%","日付":"2015-05-31T15:36:12.867Z"}]