[{"_id":"5641e957fd1ef1594b89cee6","決算期":"2007年3月期","証券コード":"7584","会社名":"丸紅インフォテック(株)【7584】","会計方式":"日本方式","決算発表日":"2007年5月17日","決算月数":"12か月","売上高":"143,818百万円","営業利益":"329百万円","経常利益":"51百万円","当期利益":"-1,658百万円","EPS（一株当たり利益）":"-114.67円","調整一株当たり利益":"---","BPS（一株当たり純資産）":"145.87円","総資産":"54,176百万円","自己資本":"2,109百万円","資本金":"921百万円","有利子負債":"18,966百万円","自己資本比率":"3.9%","ROA（総資産利益率）":"-3.07%","ROE（自己資本利益率）":"-54.83%","総資産経常利益率":"0.09%","日付":"2015-11-10T12:55:55.271Z"},{"_id":"5641e957fd1ef1594b89cee7","決算期":"2006年3月期","証券コード":"7584","会社名":"丸紅インフォテック(株)【7584】","会計方式":"日本方式","決算発表日":"2006年5月17日","決算月数":"12か月","売上高":"149,194百万円","営業利益":"-143百万円","経常利益":"-300百万円","当期利益":"-504百万円","EPS（一株当たり利益）":"-34.87円","調整一株当たり利益":"---","BPS（一株当たり純資産）":"272.38円","総資産":"53,907百万円","自己資本":"3,939百万円","資本金":"921百万円","有利子負債":"19,407百万円","自己資本比率":"7.3%","ROA（総資産利益率）":"-0.92%","ROE（自己資本利益率）":"-11.81%","総資産経常利益率":"-0.54%","日付":"2015-11-10T12:55:55.271Z"},{"_id":"5641e957fd1ef1594b89cee8","決算期":"2005年3月期","証券コード":"7584","会社名":"丸紅インフォテック(株)【7584】","会計方式":"日本方式","決算発表日":"2005年5月17日","決算月数":"12か月","売上高":"141,521百万円","営業利益":"485百万円","経常利益":"527百万円","当期利益":"116百万円","EPS（一株当たり利益）":"10.29円","調整一株当たり利益":"10.25円","BPS（一株当たり純資産）":"317.87円","総資産":"56,226百万円","自己資本":"4,599百万円","資本金":"920百万円","有利子負債":"20,943百万円","自己資本比率":"8.2%","ROA（総資産利益率）":"0.22%","ROE（自己資本利益率）":"2.69%","総資産経常利益率":"1.02%","日付":"2015-11-10T12:55:55.271Z"}]