[{"_id":"556b2a7dfac443afdd394323","決算期":"2015年3月期","証券コード":"7637","会社名":"白銅(株)【7637】","会計方式":"日本方式","決算発表日":"2015年5月13日","決算月数":"12か月","売上高":"29,923百万円","営業利益":"2,038百万円","経常利益":"2,072百万円","当期利益":"1,350百万円","EPS（一株当たり利益）":"105.44円","調整一株当たり利益":"---","BPS（一株当たり純資産）":"1,192.51円","総資産":"25,191百万円","自己資本":"13,525百万円","資本金":"1,000百万円","有利子負債":"---","自己資本比率":"53.7%","ROA（総資産利益率）":"5.58%","ROE（自己資本利益率）":"9.83%","総資産経常利益率":"8.56%","日付":"2015-05-31T15:36:29.371Z"},{"_id":"556b2a7dfac443afdd394324","決算期":"2014年3月期","証券コード":"7637","会社名":"白銅(株)【7637】","会計方式":"日本方式","決算発表日":"2014年5月12日","決算月数":"12か月","売上高":"25,570百万円","営業利益":"1,665百万円","経常利益":"1,703百万円","当期利益":"1,060百万円","EPS（一株当たり利益）":"82.56円","調整一株当たり利益":"---","BPS（一株当たり純資産）":"1,086.42円","総資産":"23,235百万円","自己資本":"13,948百万円","資本金":"1,000百万円","有利子負債":"---","自己資本比率":"60.0%","ROA（総資産利益率）":"4.75%","ROE（自己資本利益率）":"7.81%","総資産経常利益率":"7.63%","日付":"2015-05-31T15:36:29.371Z"},{"_id":"556b2a7dfac443afdd394325","決算期":"2013年3月期","証券コード":"7637","会社名":"白銅(株)【7637】","会計方式":"日本方式","決算発表日":"2013年5月10日","決算月数":"12か月","売上高":"22,150百万円","営業利益":"1,380百万円","経常利益":"1,366百万円","当期利益":"826百万円","EPS（一株当たり利益）":"64.41円","調整一株当たり利益":"---","BPS（一株当たり純資産）":"1,027.06円","総資産":"21,422百万円","自己資本":"13,186百万円","資本金":"1,000百万円","有利子負債":"---","自己資本比率":"61.6%","ROA（総資産利益率）":"3.97%","ROE（自己資本利益率）":"6.42%","総資産経常利益率":"6.57%","日付":"2015-05-31T15:36:29.371Z"}]