[{"_id":"5567367dfac443afdd393b30","決算期":"2011年3月期","証券コード":"7728","会社名":"日本電産トーソク(株)【7728】","会計方式":"日本方式","決算発表日":"2011年4月25日","決算月数":"12か月","売上高":"29,946百万円","営業利益":"4,009百万円","経常利益":"4,033百万円","当期利益":"2,366百万円","EPS（一株当たり利益）":"61.49円","調整一株当たり利益":"---","BPS（一株当たり純資産）":"541.87円","総資産":"36,682百万円","自己資本":"20,851百万円","資本金":"5,087百万円","有利子負債":"762百万円","自己資本比率":"56.8%","ROA（総資産利益率）":"7.06%","ROE（自己資本利益率）":"11.82%","総資産経常利益率":"12.04%","日付":"2015-05-31T15:35:51.383Z"},{"_id":"5567367dfac443afdd393b31","決算期":"2013年3月期","証券コード":"7728","会社名":"日本電産トーソク(株)【7728】","会計方式":"日本方式","決算発表日":"2013年4月23日","決算月数":"12か月","売上高":"31,280百万円","営業利益":"1,715百万円","経常利益":"1,974百万円","当期利益":"1,091百万円","EPS（一株当たり利益）":"28.49円","調整一株当たり利益":"---","BPS（一株当たり純資産）":"599.74円","総資産":"43,566百万円","自己資本":"22,927百万円","資本金":"5,087百万円","有利子負債":"2,600百万円","自己資本比率":"52.6%","ROA（総資産利益率）":"2.67%","ROE（自己資本利益率）":"4.84%","総資産経常利益率":"4.84%","日付":"2015-05-31T15:35:51.383Z"},{"_id":"5567367dfac443afdd393b32","決算期":"2012年3月期","証券コード":"7728","会社名":"日本電産トーソク(株)【7728】","会計方式":"日本方式","決算発表日":"2012年4月24日","決算月数":"12か月","売上高":"33,508百万円","営業利益":"3,140百万円","経常利益":"3,087百万円","当期利益":"1,844百万円","EPS（一株当たり利益）":"47.94円","調整一株当たり利益":"---","BPS（一株当たり純資産）":"575.78円","総資産":"38,035百万円","自己資本":"22,157百万円","資本金":"5,087百万円","有利子負債":"2,343百万円","自己資本比率":"58.3%","ROA（総資産利益率）":"4.94%","ROE（自己資本利益率）":"8.58%","総資産経常利益率":"8.26%","日付":"2015-05-31T15:35:51.383Z"}]