[{"会社名":"前田工繊(株)【7821】","証券コード":"7821","　":"前期","決算期":"2014年9月期","会計方式":"日本方式","決算発表日":"2014年10月31日","決算月数":"12か月","売上高":"24,571百万円","営業利益":"3,286百万円","経常利益":"3,324百万円","当期利益":"2,146百万円","EPS（一株当たり利益）":"71.56円","調整一株当たり利益":"---","BPS（一株当たり純資産）":"603.31円","総資産":"28,379百万円","自己資本":"19,442百万円","資本金":"3,438百万円","有利子負債":"1,100百万円","自己資本比率":"68.5%","ROA（総資産利益率）":"8.44%","ROE（自己資本利益率）":"12.83%","総資産経常利益率":"13.08%"},{"会社名":"前田工繊(株)【7821】","証券コード":"7821","　":"2期前","決算期":"2013年9月期","会計方式":"日本方式","決算発表日":"2013年11月1日","決算月数":"12か月","売上高":"19,906百万円","営業利益":"2,412百万円","経常利益":"2,554百万円","当期利益":"1,521百万円","EPS（一株当たり利益）":"52.50円","調整一株当たり利益":"52.47円","BPS（一株当たり純資産）":"479.31円","総資産":"22,453百万円","自己資本":"14,008百万円","資本金":"1,683百万円","有利子負債":"2,000百万円","自己資本比率":"62.4%","ROA（総資産利益率）":"7.57%","ROE（自己資本利益率）":"11.99%","総資産経常利益率":"12.72%"},{"会社名":"前田工繊(株)【7821】","証券コード":"7821","　":"3期前","決算期":"2012年9月期","会計方式":"日本方式","決算発表日":"2012年11月2日","決算月数":"12か月","売上高":"16,469百万円","営業利益":"1,420百万円","経常利益":"1,429百万円","当期利益":"1,176百万円","EPS（一株当たり利益）":"234.32円","調整一株当たり利益":"233.77円","BPS（一株当たり純資産）":"2,256.35円","総資産":"17,715百万円","自己資本":"11,363百万円","資本金":"1,044百万円","有利子負債":"900百万円","自己資本比率":"64.1%","ROA（総資産利益率）":"7.11%","ROE（自己資本利益率）":"10.83%","総資産経常利益率":"8.64%"}]