[{"_id":"5562fdd2ee6e1634eb061239","決算期":"2013年3月期","証券コード":"7871","会社名":"フクビ化学工業(株)【7871】","会計方式":"日本方式","決算発表日":"2013年5月10日","決算月数":"12か月","売上高":"38,294百万円","営業利益":"1,259百万円","経常利益":"1,417百万円","当期利益":"790百万円","EPS（一株当たり利益）":"38.34円","調整一株当たり利益":"---","BPS（一株当たり純資産）":"1,188.21円","総資産":"41,697百万円","自己資本":"24,497百万円","資本金":"2,194百万円","有利子負債":"987百万円","自己資本比率":"58.8%","ROA（総資産利益率）":"1.90%","ROE（自己資本利益率）":"3.28%","総資産経常利益率":"3.41%","日付":"2015-05-31T15:08:34.739Z"},{"_id":"5562fdd2ee6e1634eb06123a","決算期":"2014年3月期","証券コード":"7871","会社名":"フクビ化学工業(株)【7871】","会計方式":"日本方式","決算発表日":"2014年5月14日","決算月数":"12か月","売上高":"40,483百万円","営業利益":"1,597百万円","経常利益":"1,744百万円","当期利益":"1,029百万円","EPS（一株当たり利益）":"49.90円","調整一株当たり利益":"---","BPS（一株当たり純資産）":"1,224.82円","総資産":"43,669百万円","自己資本":"25,251百万円","資本金":"2,194百万円","有利子負債":"805百万円","自己資本比率":"57.8%","ROA（総資産利益率）":"2.41%","ROE（自己資本利益率）":"4.14%","総資産経常利益率":"4.09%","日付":"2015-05-31T15:08:34.740Z"},{"_id":"5562fdd2ee6e1634eb06123b","決算期":"2015年3月期","証券コード":"7871","会社名":"フクビ化学工業(株)【7871】","会計方式":"日本方式","決算発表日":"2015年5月14日","決算月数":"12か月","売上高":"38,159百万円","営業利益":"1,088百万円","経常利益":"1,268百万円","当期利益":"716百万円","EPS（一株当たり利益）":"34.71円","調整一株当たり利益":"---","BPS（一株当たり純資産）":"1,294.44円","総資産":"44,411百万円","自己資本":"26,685百万円","資本金":"2,194百万円","有利子負債":"621百万円","自己資本比率":"60.1%","ROA（総資産利益率）":"1.63%","ROE（自己資本利益率）":"2.76%","総資産経常利益率":"2.88%","日付":"2015-05-31T15:08:34.740Z"}]