[{"_id":"5562fdd5ee6e1634eb0612c8","決算期":"2010年3月期","証券コード":"7934","会社名":"メルクス(株)【7934】","会計方式":"日本方式","決算発表日":"2010年5月14日","決算月数":"12か月","売上高":"3,390百万円","営業利益":"-518百万円","経常利益":"-567百万円","当期利益":"-519百万円","EPS（一株当たり利益）":"-26.39円","調整一株当たり利益":"---","BPS（一株当たり純資産）":"60.02円","総資産":"4,337百万円","自己資本":"1,180百万円","資本金":"2,892百万円","有利子負債":"2,521百万円","自己資本比率":"27.2%","ROA（総資産利益率）":"-9.98%","ROE（自己資本利益率）":"-35.60%","総資産経常利益率":"-10.90%","日付":"2015-05-31T15:08:23.618Z"},{"_id":"5562fdd5ee6e1634eb0612c9","決算期":"2011年3月期","証券コード":"7934","会社名":"メルクス(株)【7934】","会計方式":"日本方式","決算発表日":"2011年5月13日","決算月数":"12か月","売上高":"3,917百万円","営業利益":"-434百万円","経常利益":"-513百万円","当期利益":"-525百万円","EPS（一株当たり利益）":"-26.71円","調整一株当たり利益":"---","BPS（一株当たり純資産）":"31.55円","総資産":"3,556百万円","自己資本":"620百万円","資本金":"2,892百万円","有利子負債":"2,246百万円","自己資本比率":"17.4%","ROA（総資産利益率）":"-13.30%","ROE（自己資本利益率）":"-58.33%","総資産経常利益率":"-13.00%","日付":"2015-05-31T15:08:23.618Z"},{"_id":"5562fdd5ee6e1634eb0612ca","決算期":"2009年3月期","証券コード":"7934","会社名":"メルクス(株)【7934】","会計方式":"日本方式","決算発表日":"2009年5月15日","決算月数":"12か月","売上高":"6,058百万円","営業利益":"-587百万円","経常利益":"-736百万円","当期利益":"-1,039百万円","EPS（一株当たり利益）":"-52.80円","調整一株当たり利益":"---","BPS（一株当たり純資産）":"88.26円","総資産":"6,069百万円","自己資本":"1,736百万円","資本金":"2,892百万円","有利子負債":"3,652百万円","自己資本比率":"28.6%","ROA（総資産利益率）":"-14.35%","ROE（自己資本利益率）":"-44.53%","総資産経常利益率":"-10.17%","日付":"2015-05-31T15:08:23.618Z"}]