[{"会社名":"(株)名古屋銀行【8522】","証券コード":"8522","　":"前期","決算期":"2014年3月期","会計方式":"日本方式","決算発表日":"2014年5月13日","決算月数":"12か月","売上高":"61,994百万円","営業利益":"10,269百万円","経常利益":"10,140百万円","当期利益":"5,440百万円","EPS（一株当たり利益）":"26.58円","調整一株当たり利益":"---","BPS（一株当たり純資産）":"991.57円","総資産":"3,299,106百万円","自己資本":"202,895百万円","資本金":"25,090百万円","有利子負債":"---","自己資本比率":"6.1%","ROA（総資産利益率）":"0.17%","ROE（自己資本利益率）":"2.76%","総資産経常利益率":"0.31%"},{"会社名":"(株)名古屋銀行【8522】","証券コード":"8522","　":"2期前","決算期":"2013年3月期","会計方式":"日本方式","決算発表日":"2013年5月14日","決算月数":"12か月","売上高":"62,602百万円","営業利益":"10,886百万円","経常利益":"8,433百万円","当期利益":"6,223百万円","EPS（一株当たり利益）":"30.41円","調整一株当たり利益":"---","BPS（一株当たり純資産）":"936.60円","総資産":"3,236,427百万円","自己資本":"191,668百万円","資本金":"25,090百万円","有利子負債":"---","自己資本比率":"5.9%","ROA（総資産利益率）":"0.19%","ROE（自己資本利益率）":"3.45%","総資産経常利益率":"0.26%"},{"会社名":"(株)名古屋銀行【8522】","証券コード":"8522","　":"3期前","決算期":"2012年3月期","会計方式":"日本方式","決算発表日":"2012年5月15日","決算月数":"12か月","売上高":"66,455百万円","営業利益":"11,544百万円","経常利益":"5,950百万円","当期利益":"2,089百万円","EPS（一株当たり利益）":"10.20円","調整一株当たり利益":"---","BPS（一株当たり純資産）":"826.81円","総資産":"3,172,177百万円","自己資本":"169,217百万円","資本金":"25,090百万円","有利子負債":"---","自己資本比率":"5.3%","ROA（総資産利益率）":"0.07%","ROE（自己資本利益率）":"1.26%","総資産経常利益率":"0.19%"}]