[{"_id":"5562f8d6fac443afdd392fc6","決算期":"2015年3月期","証券コード":"8543","会社名":"(株)みなと銀行【8543】","会計方式":"日本方式","決算発表日":"2015年5月13日","決算月数":"12か月","売上高":"65,043百万円","営業利益":"‥百万円","経常利益":"13,554百万円","当期利益":"7,478百万円","EPS（一株当たり利益）":"18.38円","調整一株当たり利益":"18.34円","BPS（一株当たり純資産）":"333.97円","総資産":"3,417,209百万円","自己資本":"136,024百万円","資本金":"27,484百万円","有利子負債":"---","自己資本比率":"4.0%","ROA（総資産利益率）":"0.22%","ROE（自己資本利益率）":"5.81%","総資産経常利益率":"0.40%","日付":"2015-05-31T16:06:30.798Z"},{"_id":"5562f8d6fac443afdd392fc7","決算期":"2014年3月期","証券コード":"8543","会社名":"(株)みなと銀行【8543】","会計方式":"日本方式","決算発表日":"2014年5月14日","決算月数":"12か月","売上高":"67,977百万円","営業利益":"‥百万円","経常利益":"14,178百万円","当期利益":"7,511百万円","EPS（一株当たり利益）":"18.50円","調整一株当たり利益":"18.48円","BPS（一株当たり純資産）":"298.37円","総資産":"3,340,992百万円","自己資本":"121,274百万円","資本金":"27,484百万円","有利子負債":"---","自己資本比率":"3.6%","ROA（総資産利益率）":"0.23%","ROE（自己資本利益率）":"6.30%","総資産経常利益率":"0.44%","日付":"2015-05-31T16:06:30.798Z"},{"_id":"5562f8d6fac443afdd392fc8","決算期":"2013年3月期","証券コード":"8543","会社名":"(株)みなと銀行【8543】","会計方式":"日本方式","決算発表日":"2013年5月13日","決算月数":"12か月","売上高":"65,174百万円","営業利益":"‥百万円","経常利益":"12,332百万円","当期利益":"6,949百万円","EPS（一株当たり利益）":"17.16円","調整一株当たり利益":"17.15円","BPS（一株当たり純資産）":"289.38円","総資産":"3,169,835百万円","自己資本":"117,330百万円","資本金":"27,484百万円","有利子負債":"---","自己資本比率":"3.7%","ROA（総資産利益率）":"0.22%","ROE（自己資本利益率）":"6.18%","総資産経常利益率":"0.39%","日付":"2015-05-31T16:06:30.799Z"}]