[{"_id":"5562fdf2ee6e1634eb0616ed","決算期":"2009年3月期","証券コード":"8561","会社名":"(株)徳島銀行【8561】","会計方式":"日本方式","決算発表日":"2009年5月14日","決算月数":"12か月","売上高":"28,622百万円","営業利益":"‥百万円","経常利益":"-11,243百万円","当期利益":"-6,978百万円","EPS（一株当たり利益）":"-90.40円","調整一株当たり利益":"---","BPS（一株当たり純資産）":"727.23円","総資産":"1,191,714百万円","自己資本":"56,127百万円","資本金":"11,036百万円","有利子負債":"---","自己資本比率":"4.7%","ROA（総資産利益率）":"-0.59%","ROE（自己資本利益率）":"-11.41%","総資産経常利益率":"-0.95%","日付":"2015-05-31T15:08:54.505Z"},{"_id":"5562fdf2ee6e1634eb0616ee","決算期":"2007年3月期","証券コード":"8561","会社名":"(株)徳島銀行【8561】","会計方式":"日本方式","決算発表日":"2007年5月14日","決算月数":"12か月","売上高":"29,876百万円","営業利益":"‥百万円","経常利益":"4,318百万円","当期利益":"2,204百万円","EPS（一株当たり利益）":"28.54円","調整一株当たり利益":"---","BPS（一株当たり純資産）":"959.05円","総資産":"1,158,303百万円","自己資本":"74,068百万円","資本金":"11,036百万円","有利子負債":"---","自己資本比率":"6.3%","ROA（総資産利益率）":"0.19%","ROE（自己資本利益率）":"3.03%","総資産経常利益率":"0.38%","日付":"2015-05-31T15:08:54.505Z"},{"_id":"5562fdf2ee6e1634eb0616ef","決算期":"2008年3月期","証券コード":"8561","会社名":"(株)徳島銀行【8561】","会計方式":"日本方式","決算発表日":"2008年5月16日","決算月数":"12か月","売上高":"33,081百万円","営業利益":"‥百万円","経常利益":"1,714百万円","当期利益":"574百万円","EPS（一株当たり利益）":"7.44円","調整一株当たり利益":"---","BPS（一株当たり純資産）":"857.85円","総資産":"1,177,816百万円","自己資本":"66,228百万円","資本金":"11,036百万円","有利子負債":"---","自己資本比率":"5.6%","ROA（総資産利益率）":"0.05%","ROE（自己資本利益率）":"0.82%","総資産経常利益率":"0.15%","日付":"2015-05-31T15:08:54.506Z"}]