[{"_id":"551f8a3331cae9239deb2f24","会社名":"三菱地所(株)【8802】","証券コード":"8802","決算期":"2014年3月期","会計方式":"日本方式","決算発表日":"2014年5月8日","決算月数":"12か月","売上高":"1,075,285百万円","営業利益":"161,271百万円","経常利益":"139,638百万円","当期利益":"64,297百万円","EPS（一株当たり利益）":"46.34円","調整一株当たり利益":"46.32円","BPS（一株当たり純資産）":"957.80円","総資産":"4,765,368百万円","自己資本":"1,329,059百万円","資本金":"141,373百万円","有利子負債":"1,963,536百万円","自己資本比率":"27.9%","ROA（総資産利益率）":"1.36%","ROE（自己資本利益率）":"5.01%","総資産経常利益率":"2.95%","__v":0,"日付":"2015-04-04T06:52:35.183Z"},{"_id":"551f8a3331cae9239deb2f25","会社名":"三菱地所(株)【8802】","証券コード":"8802","決算期":"2013年3月期","会計方式":"日本方式","決算発表日":"2013年5月7日","決算月数":"12か月","売上高":"927,157百万円","営業利益":"118,349百万円","経常利益":"92,381百万円","当期利益":"45,507百万円","EPS（一株当たり利益）":"32.79円","調整一株当たり利益":"32.78円","BPS（一株当たり純資産）":"893.27円","総資産":"4,711,521百万円","自己資本":"1,239,548百万円","資本金":"141,373百万円","有利子負債":"2,075,207百万円","自己資本比率":"26.3%","ROA（総資産利益率）":"1.00%","ROE（自己資本利益率）":"3.65%","総資産経常利益率":"2.03%","__v":0,"日付":"2015-04-04T06:52:35.183Z"},{"_id":"551f8a3331cae9239deb2f26","会社名":"三菱地所(株)【8802】","証券コード":"8802","決算期":"2012年3月期","会計方式":"日本方式","決算発表日":"2012年5月7日","決算月数":"12か月","売上高":"1,013,069百万円","営業利益":"146,299百万円","経常利益":"120,665百万円","当期利益":"56,512百万円","EPS（一株当たり利益）":"40.72円","調整一株当たり利益":"40.71円","BPS（一株当たり純資産）":"905.60円","総資産":"4,387,015百万円","自己資本":"1,256,792百万円","資本金":"141,373百万円","有利子負債":"1,708,567百万円","自己資本比率":"28.6%","ROA（総資産利益率）":"1.31%","ROE（自己資本利益率）":"4.60%","総資産経常利益率":"2.80%","__v":0,"日付":"2015-04-04T06:52:35.183Z"}]