[{"_id":"551f8a5131cae9239deb32a2","会社名":"(株)ストライダーズ【9816】","証券コード":"9816","決算期":"2014年3月期","会計方式":"日本方式","決算発表日":"2014年5月14日","決算月数":"12か月","売上高":"2,690百万円","営業利益":"45百万円","経常利益":"91百万円","当期利益":"133百万円","EPS（一株当たり利益）":"1.64円","調整一株当たり利益":"1.62円","BPS（一株当たり純資産）":"13.32円","総資産":"2,309百万円","自己資本":"1,113百万円","資本金":"1,403百万円","有利子負債":"552百万円","自己資本比率":"48.2%","ROA（総資産利益率）":"6.18%","ROE（自己資本利益率）":"12.84%","総資産経常利益率":"4.23%","__v":0,"日付":"2015-04-04T06:53:05.278Z"},{"_id":"551f8a5131cae9239deb32a3","会社名":"(株)ストライダーズ【9816】","証券コード":"9816","決算期":"2013年3月期","会計方式":"日本方式","決算発表日":"2013年5月14日","決算月数":"12か月","売上高":"1,689百万円","営業利益":"-147百万円","経常利益":"-113百万円","当期利益":"-353百万円","EPS（一株当たり利益）":"-4.74円","調整一株当たり利益":"---","BPS（一株当たり純資産）":"11.93円","総資産":"1,992百万円","自己資本":"959百万円","資本金":"1,371百万円","有利子負債":"346百万円","自己資本比率":"48.1%","ROA（総資産利益率）":"-18.89%","ROE（自己資本利益率）":"-33.33%","総資産経常利益率":"-6.05%","__v":0,"日付":"2015-04-04T06:53:05.279Z"},{"_id":"551f8a5131cae9239deb32a4","会社名":"(株)ストライダーズ【9816】","証券コード":"9816","決算期":"2012年3月期","会計方式":"日本方式","決算発表日":"2012年5月14日","決算月数":"12か月","売上高":"1,080百万円","営業利益":"-233百万円","経常利益":"-183百万円","当期利益":"-121百万円","EPS（一株当たり利益）":"-1.62円","調整一株当たり利益":"---","BPS（一株当たり純資産）":"15.60円","総資産":"1,746百万円","自己資本":"1,159百万円","資本金":"1,314百万円","有利子負債":"72百万円","自己資本比率":"66.4%","ROA（総資産利益率）":"-4.45%","ROE（自己資本利益率）":"-10.07%","総資産経常利益率":"-6.73%","__v":0,"日付":"2015-04-04T06:53:05.279Z"}]