[{"_id":"5641e955fd1ef1594b89cd8a","決算期":"2009年3月期","証券コード":"9844","会社名":"(株)ユーエスシー【9844】","会計方式":"日本方式","決算発表日":"2009年5月14日","決算月数":"12か月","売上高":"187,121百万円","営業利益":"3,008百万円","経常利益":"1,844百万円","当期利益":"243百万円","EPS（一株当たり利益）":"21.65円","調整一株当たり利益":"---","BPS（一株当たり純資産）":"2,307.49円","総資産":"47,466百万円","自己資本":"25,953百万円","資本金":"3,184百万円","有利子負債":"5,295百万円","自己資本比率":"54.7%","ROA（総資産利益率）":"0.38%","ROE（自己資本利益率）":"0.92%","総資産経常利益率":"2.91%","日付":"2015-11-10T12:55:55.257Z"},{"_id":"5641e955fd1ef1594b89cd8b","決算期":"2008年3月期","証券コード":"9844","会社名":"(株)ユーエスシー【9844】","会計方式":"日本方式","決算発表日":"2008年5月12日","決算月数":"12か月","売上高":"234,447百万円","営業利益":"4,235百万円","経常利益":"3,713百万円","当期利益":"1,948百万円","EPS（一株当たり利益）":"173.21円","調整一株当たり利益":"---","BPS（一株当たり純資産）":"2,387.11円","総資産":"79,434百万円","自己資本":"26,850百万円","資本金":"3,184百万円","有利子負債":"8,130百万円","自己資本比率":"33.8%","ROA（総資産利益率）":"2.61%","ROE（自己資本利益率）":"7.30%","総資産経常利益率":"4.97%","日付":"2015-11-10T12:55:55.257Z"},{"_id":"5641e955fd1ef1594b89cd8c","決算期":"2007年3月期","証券コード":"9844","会社名":"(株)ユーエスシー【9844】","会計方式":"日本方式","決算発表日":"2007年5月7日","決算月数":"12か月","売上高":"198,220百万円","営業利益":"3,973百万円","経常利益":"4,020百万円","当期利益":"2,359百万円","EPS（一株当たり利益）":"209.73円","調整一株当たり利益":"---","BPS（一株当たり純資産）":"2,360.32円","総資産":"70,050百万円","自己資本":"26,550百万円","資本金":"3,184百万円","有利子負債":"6,814百万円","自己資本比率":"37.9%","ROA（総資産利益率）":"3.37%","ROE（自己資本利益率）":"9.20%","総資産経常利益率":"5.74%","日付":"2015-11-10T12:55:55.258Z"}]