[{"_id":"5641e956fd1ef1594b89cde1","決算期":"2015年2月期","証券コード":"9974","会社名":"(株)ベルク【9974】","会計方式":"日本方式","決算発表日":"2015年4月9日","決算月数":"12か月","売上高":"161,125百万円","営業利益":"7,283百万円","経常利益":"7,541百万円","当期利益":"4,465百万円","EPS（一株当たり利益）":"213.97円","調整一株当たり利益":"---","BPS（一株当たり純資産）":"2,080.42円","総資産":"87,497百万円","自己資本":"43,412百万円","資本金":"3,912百万円","有利子負債":"18,911百万円","自己資本比率":"49.6%","ROA（総資産利益率）":"5.43%","ROE（自己資本利益率）":"10.72%","総資産経常利益率":"9.17%","日付":"2015-11-10T12:55:55.341Z"},{"_id":"5641e956fd1ef1594b89cde2","決算期":"2014年2月期","証券コード":"9974","会社名":"(株)ベルク【9974】","会計方式":"日本方式","決算発表日":"2014年4月9日","決算月数":"12か月","売上高":"145,024百万円","営業利益":"6,887百万円","経常利益":"7,134百万円","当期利益":"3,992百万円","EPS（一株当たり利益）":"191.31円","調整一株当たり利益":"---","BPS（一株当たり純資産）":"1,912.74円","総資産":"76,913百万円","自己資本":"39,913百万円","資本金":"3,912百万円","有利子負債":"16,269百万円","自己資本比率":"51.9%","ROA（総資産利益率）":"5.43%","ROE（自己資本利益率）":"10.42%","総資産経常利益率":"9.71%","日付":"2015-11-10T12:55:55.341Z"},{"_id":"5641e956fd1ef1594b89cde3","決算期":"2013年2月期","証券コード":"9974","会社名":"(株)ベルク【9974】","会計方式":"日本方式","決算発表日":"2013年4月10日","決算月数":"12か月","売上高":"133,109百万円","営業利益":"6,375百万円","経常利益":"6,608百万円","当期利益":"3,394百万円","EPS（一株当たり利益）":"162.70円","調整一株当たり利益":"---","BPS（一株当たり純資産）":"1,759.45円","総資産":"70,061百万円","自己資本":"36,714百万円","資本金":"3,912百万円","有利子負債":"15,176百万円","自己資本比率":"52.4%","ROA（総資産利益率）":"5.14%","ROE（自己資本利益率）":"9.59%","総資産経常利益率":"10.00%","日付":"2015-11-10T12:55:55.341Z"}]