[{"会社名":"(株)ベルク【9974】","証券コード":"9974","　":"前期","決算期":"2014年2月期","会計方式":"日本方式","決算発表日":"2014年4月9日","決算月数":"12か月","売上高":"145,024百万円","営業利益":"6,887百万円","経常利益":"7,134百万円","当期利益":"3,992百万円","EPS（一株当たり利益）":"191.31円","調整一株当たり利益":"---","BPS（一株当たり純資産）":"1,912.74円","総資産":"76,913百万円","自己資本":"39,913百万円","資本金":"3,912百万円","有利子負債":"16,269百万円","自己資本比率":"51.9%","ROA（総資産利益率）":"5.43%","ROE（自己資本利益率）":"10.42%","総資産経常利益率":"9.71%"},{"会社名":"(株)ベルク【9974】","証券コード":"9974","　":"2期前","決算期":"2013年2月期","会計方式":"日本方式","決算発表日":"2013年4月10日","決算月数":"12か月","売上高":"133,109百万円","営業利益":"6,375百万円","経常利益":"6,608百万円","当期利益":"3,394百万円","EPS（一株当たり利益）":"162.70円","調整一株当たり利益":"---","BPS（一株当たり純資産）":"1,759.45円","総資産":"70,061百万円","自己資本":"36,714百万円","資本金":"3,912百万円","有利子負債":"15,176百万円","自己資本比率":"52.4%","ROA（総資産利益率）":"5.14%","ROE（自己資本利益率）":"9.59%","総資産経常利益率":"10.00%"},{"会社名":"(株)ベルク【9974】","証券コード":"9974","　":"3期前","決算期":"2012年2月期","会計方式":"日本方式","決算発表日":"2012年4月11日","決算月数":"12か月","売上高":"123,925百万円","営業利益":"6,250百万円","経常利益":"6,464百万円","当期利益":"3,389百万円","EPS（一株当たり利益）":"162.45円","調整一株当たり利益":"---","BPS（一株当たり純資産）":"1,632.37円","総資産":"62,072百万円","自己資本":"34,062百万円","資本金":"3,912百万円","有利子負債":"11,175百万円","自己資本比率":"54.9%","ROA（総資産利益率）":"5.68%","ROE（自己資本利益率）":"10.36%","総資産経常利益率":"10.84%"}]